napari_cilia_beating_frequency/__init__.py
napari_cilia_beating_frequency/napari.toml
napari_cilia_beating_frequency-0.2.dist-info/METADATA
napari_cilia_beating_frequency-0.2.dist-info/WHEEL
napari_cilia_beating_frequency-0.2.dist-info/entry_points.txt
napari_cilia_beating_frequency-0.2.dist-info/top_level.txt
napari_cilia_beating_frequency-0.2.dist-info/RECORD
